README.md
setup.cfg
setup.py
bigbang/__init__.py
bigbang/command_line.py
bigbang/text.py
bigbang.egg-info/PKG-INFO
bigbang.egg-info/SOURCES.txt
bigbang.egg-info/dependency_links.txt
bigbang.egg-info/entry_points.txt
bigbang.egg-info/not-zip-safe
bigbang.egg-info/requires.txt
bigbang.egg-info/top_level.txt