Metadata-Version: 1.0
Name: bigbang
Version: 0.1.9
Summary: Library to create development environment
Home-page: https://github.com/Fabfm4/bigbang-python
Author: Sergio Fabian Flores Mendoza
Author-email: favian.flone92@gmail.com
License: MIT
Platform: UNKNOWN
